pycsp3_explain/__init__.py
pycsp3_explain/explain/__init__.py
pycsp3_explain/explain/marco.py
pycsp3_explain/explain/mss.py
pycsp3_explain/explain/mus.py
pycsp3_explain/explain/utils.py
pycsp3_explain/solvers/__init__.py
pycsp3_explain/solvers/wrapper.py
pycsp3_explain-0.3.0.dist-info/METADATA
pycsp3_explain-0.3.0.dist-info/WHEEL
pycsp3_explain-0.3.0.dist-info/RECORD
