Metadata-Version: 2.4
Name: pycsp3-explain
Version: 0.3.0
Summary: Explanation tools for PyCSP3 constraint models
Project-URL: Homepage, https://github.com/sohaibafifi/pycsp3-explain
Project-URL: Repository, https://github.com/sohaibafifi/pycsp3-explain
Project-URL: Issues, https://github.com/sohaibafifi/pycsp3-explain/issues
Author-email: Sohaib AFIFI <sohaib.lafifi@univ-artois.fr>
License: MIT
Keywords: constraint-programming,explain,pycsp3,xcsp3
Classifier: Development Status :: 3 - Alpha
Classifier: Intended Audience :: Developers
Classifier: Intended Audience :: Science/Research
Classifier: License :: OSI Approved :: MIT License
Classifier: Operating System :: OS Independent
Classifier: Programming Language :: Python :: 3
Classifier: Programming Language :: Python :: 3.10
Classifier: Programming Language :: Python :: 3.11
Classifier: Programming Language :: Python :: 3.12
Classifier: Topic :: Scientific/Engineering
Classifier: Topic :: Scientific/Engineering :: Artificial Intelligence
Requires-Python: >=3.10
Requires-Dist: lxml>=4.9
Requires-Dist: pycsp3>=2.5
Provides-Extra: dev
Requires-Dist: mypy>=1.0; extra == 'dev'
Requires-Dist: pytest-cov>=4.0; extra == 'dev'
Requires-Dist: pytest>=7.0; extra == 'dev'
Requires-Dist: ruff>=0.1; extra == 'dev'
Provides-Extra: docs
Requires-Dist: sphinx-rtd-theme>=1.0; extra == 'docs'
Requires-Dist: sphinx>=6.0; extra == 'docs'
